{
  "weather": {
    "temperature": "18.0",
    "humidity": "44",
    "pressure": "806.56",
    "winddirection": "NNE",
    "batterypercentage": "21"
  },
  "aggregated": {
    "mintemperature": "18",
    "maxtemperature": "26",
    "barotrend": "-0.2",
    "rainhour": "0.0",
    "rainday": "0.0",
    "windmps": "0.0",
    "windmph": "0.0",
    "windknots": "0.0",
    "gustsmps": "0.0",
    "gustsmph": "0.0",
    "gustsknots": "0.0"
  },
  "sun": {
    "azimuth": "267",
    "inclination": "-68"
  },
  "updated-de": "Sun, Jan 18, 11:21 PM",
  "offline": false
}