{
  "weather": {
    "temperature": "18.8",
    "humidity": "47",
    "pressure": "804.95",
    "winddirection": "NNE",
    "batterypercentage": "27"
  },
  "aggregated": {
    "mintemperature": "19",
    "maxtemperature": "26",
    "barotrend": "0.5",
    "rainhour": "0.0",
    "rainday": "0.0",
    "windmps": "0.0",
    "windmph": "0.0",
    "windknots": "0.0",
    "gustsmps": "0.0",
    "gustsmph": "0.0",
    "gustsknots": "0.0"
  },
  "sun": {
    "azimuth": "255",
    "inclination": "-20"
  },
  "updated-de": "Sun, Jan 18, 07:51 PM",
  "offline": false
}