{
  "weather": {
    "temperature": "17.4",
    "humidity": "44",
    "pressure": "805.51",
    "winddirection": "NNE",
    "batterypercentage": "16"
  },
  "aggregated": {
    "mintemperature": "17",
    "maxtemperature": "18",
    "barotrend": "-0.0",
    "rainhour": "0.0",
    "rainday": "0.0",
    "windmps": "0.0",
    "windmph": "0.0",
    "windknots": "0.0",
    "gustsmps": "0.0",
    "gustsmph": "0.0",
    "gustsknots": "0.0"
  },
  "sun": {
    "azimuth": "94",
    "inclination": "-64"
  },
  "updated-de": "Mon, Jan 19, 02:47 AM",
  "offline": false
}