{
  "weather": {
    "temperature": "19.9",
    "humidity": "47",
    "pressure": "803.73",
    "winddirection": "NNE",
    "batterypercentage": "26"
  },
  "aggregated": {
    "mintemperature": "20",
    "maxtemperature": "26",
    "barotrend": "0.1",
    "rainhour": "0.0",
    "rainday": "0.0",
    "windmps": "0.0",
    "windmph": "0.0",
    "windknots": "0.0",
    "gustsmps": "0.0",
    "gustsmph": "0.0",
    "gustsknots": "0.0"
  },
  "sun": {
    "azimuth": "249",
    "inclination": "-1"
  },
  "updated-de": "Sun, Jan 18, 06:28 PM",
  "offline": false
}